LICENSE
pysenec/__init__.py
pysenec/cli.py
pysenec/constants.py
pysenec/util.py
pysenec-0.3.0.dist-info/entry_points.txt
pysenec-0.3.0.dist-info/LICENSE
pysenec-0.3.0.dist-info/WHEEL
pysenec-0.3.0.dist-info/METADATA
pysenec-0.3.0.dist-info/RECORD
